[{"kind": "Listing", "data": {"after": null, "dist": 1, "modhash": "", "geo_filter": "", "children": [{"kind": "t3", "data": {"approved_at_utc": null, "subreddit": "superleague", "selftext": "||**20:00**||\n|:--:|:--:|:--:|\n|[](#game-toulouse)|[](#vs)|[](#game-wigan)\n|Toulouse Olympique|Venue:| Wigan Warriors\n||Stade Ernest Wallon|\n___\n\n**Remember to make your predictions below and upvote the thread!**", "author_fullname": "t2_ci3jv", "saved": false, "mod_reason_title": null, "gilded": 0, "clicked": false, "title": "Saturday Match Thread | Round Four", "event_start": 1646499600.0, "subreddit_name_prefixed": "r/superleague", "hidden": false, "pwls": 6, "link_flair_css_class": null, "downs": 0, "thumbnail_height": null, "top_awarded_type": null, "parent_whitelist_status": "all_ads", "hide_score": false, "name": "t3_t7ct2o", "quarantine": false, "link_flair_text_color": "dark", "upvote_ratio": 1.0, "author_flair_background_color": "", "subreddit_type": "public", "ups": 7, "domain": "self.superleague", "media_embed": {}, "thumbnail_width": null, "author_flair_template_id": null, "is_original_content": false, "user_reports": [], "secure_media": null, "is_reddit_media_domain": false, "is_meta": false, "category": null, "secure_media_embed": {}, "link_flair_text": null, "can_mod_post": false, "score": 7, "approved_by": null, "is_created_from_ads_ui": false, "author_premium": false, "thumbnail": "self", "edited": false, "author_flair_css_class": "robot", "author_flair_richtext": [{"e": "text", "t": "Robot"}], "gildings": {}, "content_categories": null, "is_self": true, "mod_note": null, "created": 1646496989.0, "link_flair_type": "text", "wls": 6, "removed_by_category": null, "banned_by": null, "author_flair_type": "richtext", "total_awards_received": 0, "allow_live_comments": true, "selftext_html": "&lt;!-- SC_OFF --&gt;&lt;div class=\"md\"&gt;&lt;table&gt;&lt;thead&gt;\n&lt;tr&gt;\n&lt;th align=\"center\"&gt;&lt;/th&gt;\n&lt;th align=\"center\"&gt;&lt;strong&gt;20:00&lt;/strong&gt;&lt;/th&gt;\n&lt;th align=\"center\"&gt;&lt;/th&gt;\n&lt;/tr&gt;\n&lt;/thead&gt;&lt;tbody&gt;\n&lt;tr&gt;\n&lt;td align=\"center\"&gt;&lt;a href=\"#game-toulouse\"&gt;&lt;/a&gt;&lt;/td&gt;\n&lt;td align=\"center\"&gt;&lt;a href=\"#vs\"&gt;&lt;/a&gt;&lt;/td&gt;\n&lt;td align=\"center\"&gt;&lt;a href=\"#game-wigan\"&gt;&lt;/a&gt;&lt;/td&gt;\n&lt;/tr&gt;\n&lt;tr&gt;\n&lt;td align=\"center\"&gt;Toulouse Olympique&lt;/td&gt;\n&lt;td align=\"center\"&gt;Venue:&lt;/td&gt;\n&lt;td align=\"center\"&gt;Wigan Warriors&lt;/td&gt;\n&lt;/tr&gt;\n&lt;tr&gt;\n&lt;td align=\"center\"&gt;&lt;/td&gt;\n&lt;td align=\"center\"&gt;Stade Ernest Wallon&lt;/td&gt;\n&lt;td align=\"center\"&gt;&lt;/td&gt;\n&lt;/tr&gt;\n&lt;/tbody&gt;&lt;/table&gt;\n\n&lt;hr/&gt;\n\n&lt;p&gt;&lt;strong&gt;Remember to make your predictions below and upvote the thread!&lt;/strong&gt;&lt;/p&gt;\n&lt;/div&gt;&lt;!-- SC_ON --&gt;", "likes": null, "suggested_sort": "new", "banned_at_utc": null, "view_count": null, "archived": false, "no_follow": false, "is_crosspostable": false, "pinned": false, "over_18": false, "all_awardings": [], "awarders": [], "media_only": false, "link_flair_richtext": [], "can_gild": false, "spoiler": false, "locked": false, "author_flair_text": "Robot", "treatment_tags": [], "visited": false, "removed_by": null, "num_reports": null, "distinguished": null, "subreddit_id": "t5_2sjgl", "author_is_blocked": false, "event_end": 1646514000.0, "mod_reason_by": null, "removal_reason": null, "event_is_live": false, "link_flair_background_color": "", "id": "t7ct2o", "is_robot_indexable": true, "num_duplicates": 0, "report_reasons": null, "author": "SL_Thread", "discussion_type": "CHAT", "num_comments": 24, "send_replies": true, "media": null, "contest_mode": false, "author_patreon_flair": false, "author_flair_text_color": "dark", "permalink": "/r/superleague/comments/t7ct2o/saturday_match_thread_round_four/", "whitelist_status": "all_ads", "stickied": false, "url": "https://www.reddit.com/r/superleague/comments/t7ct2o/saturday_match_thread_round_four/", "subreddit_subscribers": 6375, "created_utc": 1646496989.0, "num_crossposts": 0, "mod_reports": [], "is_video": false}}], "before": null}}, {"kind": "Listing", "data": {"after": null, "dist": null, "modhash": "", "geo_filter": "", "children": [{"kind": "t1", "data": {"subreddit_id": "t5_2sjgl", "approved_at_utc": null, "author_is_blocked": false, "comment_type": null, "awarders": [], "mod_reason_by": null, "banned_by": null, "author_flair_type": "richtext", "total_awards_received": 0, "subreddit": "superleague", "author_flair_template_id": null, "likes": null, "replies": {"kind": "Listing", "data": {"after": null, "dist": null, "modhash": "", "geo_filter": "", "children": [{"kind": "t1", "data": {"subreddit_id": "t5_2sjgl", "approved_at_utc": null, "author_is_blocked": false, "comment_type": null, "awarders": [], "mod_reason_by": null, "banned_by": null, "author_flair_type": "richtext", "total_awards_received": 0, "subreddit": "superleague", "author_flair_template_id": null, "likes": null, "replies": {"kind": "Listing", "data": {"after": null, "dist": null, "modhash": "", "geo_filter": "", "children": [{"kind": "t1", "data": {"subreddit_id": "t5_2sjgl", "approved_at_utc": null, "author_is_blocked": false, "comment_type": null, "awarders": [], "mod_reason_by": null, "banned_by": null, "author_flair_type": "richtext", "total_awards_received": 0, "subreddit": "superleague", "author_flair_template_id": null, "likes": null, "replies": {"kind": "Listing", "data": {"after": null, "dist": null, "modhash": "", "geo_filter": "", "children": [{"kind": "t1", "data": {"subreddit_id": "t5_2sjgl", "approved_at_utc": null, "author_is_blocked": false, "comment_type": null, "awarders": [], "mod_reason_by": null, "banned_by": null, "author_flair_type": "richtext", "total_awards_received": 0, "subreddit": "superleague", "author_flair_template_id": null, "likes": null, "replies": {"kind": "Listing", "data": {"after": null, "dist": null, "modhash": "", "geo_filter": "", "children": [{"kind": "t1", "data": {"subreddit_id": "t5_2sjgl", "approved_at_utc": null, "author_is_blocked": false, "comment_type": null, "awarders": [], "mod_reason_by": null, "banned_by": null, "author_flair_type": "richtext", "total_awards_received": 0, "subreddit": "superleague", "author_flair_template_id": null, "distinguished": null, "likes": null, "replies": {"kind": "Listing", "data": {"after": null, "dist": null, "modhash": "", "geo_filter": "", "children": [{"kind": "t1", "data": {"subreddit_id": "t5_2sjgl", "approved_at_utc": null, "author_is_blocked": false, "comment_type": null, "awarders": [], "mod_reason_by": null, "banned_by": null, "author_flair_type": "richtext", "total_awards_received": 0, "subreddit": "superleague", "author_flair_template_id": null, "distinguished": null, "likes": null, "replies": "", "user_reports": [], "saved": false, "id": "hzijsd5", "banned_at_utc": null, "mod_reason_title": null, "gilded": 0, "archived": false, "collapsed_reason_code": null, "no_follow": true, "author": "SupervillainIndiana", "can_mod_post": false, "send_replies": true, "parent_id": "t1_hzienir", "score": 1, "author_fullname": "t2_j2s03", "approved_by": null, "mod_note": null, "all_awardings": [], "body": "If it makes you feel any better, I remember when we beat Widnes in the promotion final there's this one lassie whose face I'll never forget because she had one of those jester hats on (black and white in this case) and had tears streaming down her face. Anyway, she was up on the big screen, and therefore probably the Sky feed, for what would've felt like an *eternity* had that been me.", "edited": false, "gildings": {}, "downs": 0, "author_flair_css_class": "castleford-tigers", "name": "t1_hzijsd5", "is_submitter": false, "collapsed": false, "author_flair_richtext": [{"e": "text", "t": "Castleford Tigers"}], "author_patreon_flair": false, "body_html": "&lt;div class=\"md\"&gt;&lt;p&gt;If it makes you feel any better, I remember when we beat Widnes in the promotion final there&amp;#39;s this one lassie whose face I&amp;#39;ll never forget because she had one of those jester hats on (black and white in this case) and had tears streaming down her face. Anyway, she was up on the big screen, and therefore probably the Sky feed, for what would&amp;#39;ve felt like an &lt;em&gt;eternity&lt;/em&gt; had that been me.&lt;/p&gt;\n&lt;/div&gt;", "removal_reason": null, "collapsed_reason": null, "link_id": "t3_t7ct2o", "associated_award": null, "stickied": false, "author_premium": false, "can_gild": false, "top_awarded_type": null, "unrepliable_reason": null, "author_flair_text_color": "dark", "score_hidden": false, "permalink": "/r/superleague/comments/t7ct2o/saturday_match_thread_round_four/hzijsd5/", "subreddit_type": "public", "locked": false, "report_reasons": null, "created": 1646525469.0, "author_flair_text": "Castleford Tigers", "treatment_tags": [], "created_utc": 1646525469.0, "subreddit_name_prefixed": "r/superleague", "controversiality": 0, "depth": 5, "author_flair_background_color": "", "collapsed_because_crowd_control": null, "mod_reports": [], "num_reports": null, "ups": 1}}], "before": null}}, "user_reports": [], "saved": false, "id": "hzienir", "banned_at_utc": null, "mod_reason_title": null, "gilded": 0, "archived": false, "collapsed_reason_code": null, "no_follow": false, "author": "dog_west", "can_mod_post": false, "send_replies": true, "parent_id": "t1_hzibazf", "score": 4, "author_fullname": "t2_cnaq2", "removal_reason": null, "approved_by": null, "mod_note": null, "all_awardings": [], "body": "I was there. In the 20+ years I've been going to watch Train it's the one game where sky decided to zoom right in on my face in the crowd looking incredibly sad and concerned when cas were winning, which was then shown in the game highlights and on the news which I didn't really appreciate haha!", "edited": false, "author_flair_css_class": "wakefield-trinity-wildcats", "name": "t1_hzienir", "is_submitter": false, "downs": 0, "author_flair_richtext": [{"e": "text", "t": "Wakefield Trinity Wildcats"}], "author_patreon_flair": false, "body_html": "&lt;div class=\"md\"&gt;&lt;p&gt;I was there. In the 20+ years I&amp;#39;ve been going to watch Train it&amp;#39;s the one game where sky decided to zoom right in on my face in the crowd looking incredibly sad and concerned when cas were winning, which was then shown in the game highlights and on the news which I didn&amp;#39;t really appreciate haha!&lt;/p&gt;\n&lt;/div&gt;", "gildings": {}, "collapsed_reason": null, "link_id": "t3_t7ct2o", "associated_award": null, "stickied": false, "author_premium": false, "can_gild": false, "top_awarded_type": null, "unrepliable_reason": null, "author_flair_text_color": "dark", "treatment_tags": [], "score_hidden": false, "permalink": "/r/superleague/comments/t7ct2o/saturday_match_thread_round_four/hzienir/", "subreddit_type": "public", "locked": false, "report_reasons": null, "created": 1646523058.0, "author_flair_text": "Wakefield Trinity Wildcats", "collapsed": false, "created_utc": 1646523058.0, "subreddit_name_prefixed": "r/superleague", "controversiality": 0, "depth": 4, "author_flair_background_color": "", "collapsed_because_crowd_control": null, "mod_reports": [], "num_reports": null, "ups": 4}}], "before": null}}, "user_reports": [], "saved": false, "id": "hzibazf", "banned_at_utc": null, "mod_reason_title": null, "gilded": 0, "archived": false, "collapsed_reason_code": null, "no_follow": true, "author": "SupervillainIndiana", "can_mod_post": false, "send_replies": true, "parent_id": "t1_hzib2ly", "score": 2, "author_fullname": "t2_j2s03", "removal_reason": null, "approved_by": null, "mod_note": null, "all_awardings": [], "collapsed": false, "body": "I was at a pal's 21st birthday celebrations in Cardiff when that happened. Which it turns out was a good thing!", "edited": false, "top_awarded_type": null, "author_flair_css_class": "castleford-tigers", "name": "t1_hzibazf", "is_submitter": false, "downs": 0, "author_flair_richtext": [{"e": "text", "t": "Castleford Tigers"}], "author_patreon_flair": false, "body_html": "&lt;div class=\"md\"&gt;&lt;p&gt;I was at a pal&amp;#39;s 21st birthday celebrations in Cardiff when that happened. Which it turns out was a good thing!&lt;/p&gt;\n&lt;/div&gt;", "gildings": {}, "collapsed_reason": null, "distinguished": null, "associated_award": null, "stickied": false, "author_premium": false, "can_gild": false, "link_id": "t3_t7ct2o", "unrepliable_reason": null, "author_flair_text_color": "dark", "score_hidden": false, "permalink": "/r/superleague/comments/t7ct2o/saturday_match_thread_round_four/hzibazf/", "subreddit_type": "public", "locked": false, "report_reasons": null, "created": 1646521521.0, "author_flair_text": "Castleford Tigers", "treatment_tags": [], "created_utc": 1646521521.0, "subreddit_name_prefixed": "r/superleague", "controversiality": 0, "depth": 3, "author_flair_background_color": "", "collapsed_because_crowd_control": null, "mod_reports": [], "num_reports": null, "ups": 2}}], "before": null}}, "user_reports": [], "saved": false, "id": "hzib2ly", "banned_at_utc": null, "mod_reason_title": null, "gilded": 0, "archived": false, "collapsed_reason_code": null, "no_follow": true, "author": "dog_west", "can_mod_post": false, "send_replies": true, "parent_id": "t1_hzhklot", "score": 3, "author_fullname": "t2_cnaq2", "removal_reason": null, "approved_by": null, "mod_note": null, "all_awardings": [], "body": "At least the fixtures don't allow for a repeat of 2006 judgement day, don't think my heart could take that again haha", "edited": false, "top_awarded_type": null, "downs": 0, "author_flair_css_class": "wakefield-trinity-wildcats", "name": "t1_hzib2ly", "is_submitter": false, "collapsed": false, "author_flair_richtext": [{"e": "text", "t": "Wakefield Trinity Wildcats"}], "author_patreon_flair": false, "body_html": "&lt;div class=\"md\"&gt;&lt;p&gt;At least the fixtures don&amp;#39;t allow for a repeat of 2006 judgement day, don&amp;#39;t think my heart could take that again haha&lt;/p&gt;\n&lt;/div&gt;", "gildings": {}, "collapsed_reason": null, "distinguished": null, "associated_award": null, "stickied": false, "author_premium": false, "can_gild": false, "link_id": "t3_t7ct2o", "unrepliable_reason": null, "author_flair_text_color": "dark", "score_hidden": false, "permalink": "/r/superleague/comments/t7ct2o/saturday_match_thread_round_four/hzib2ly/", "subreddit_type": "public", "locked": false, "report_reasons": null, "created": 1646521417.0, "author_flair_text": "Wakefield Trinity Wildcats", "treatment_tags": [], "created_utc": 1646521417.0, "subreddit_name_prefixed": "r/superleague", "controversiality": 0, "depth": 2, "author_flair_background_color": "", "collapsed_because_crowd_control": null, "mod_reports": [], "num_reports": null, "ups": 3}}], "before": null}}, "user_reports": [], "saved": false, "id": "hzhklot", "banned_at_utc": null, "mod_reason_title": null, "gilded": 0, "archived": false, "collapsed_reason_code": null, "no_follow": false, "author": "SupervillainIndiana", "can_mod_post": false, "created_utc": 1646509461.0, "send_replies": true, "parent_id": "t1_hzhg2hj", "score": 3, "author_fullname": "t2_j2s03", "removal_reason": null, "approved_by": null, "mod_note": null, "all_awardings": [], "body": "I'm not! It's not easing my \"getting sucked into a relegation fight\" fears lurking in the back of my mind.", "edited": false, "top_awarded_type": null, "author_flair_css_class": "castleford-tigers", "name": "t1_hzhklot", "is_submitter": false, "downs": 0, "author_flair_richtext": [{"e": "text", "t": "Castleford Tigers"}], "author_patreon_flair": false, "body_html": "&lt;div class=\"md\"&gt;&lt;p&gt;I&amp;#39;m not! It&amp;#39;s not easing my &amp;quot;getting sucked into a relegation fight&amp;quot; fears lurking in the back of my mind.&lt;/p&gt;\n&lt;/div&gt;", "gildings": {}, "collapsed_reason": null, "distinguished": null, "associated_award": null, "stickied": false, "author_premium": false, "can_gild": false, "link_id": "t3_t7ct2o", "unrepliable_reason": null, "author_flair_text_color": "dark", "score_hidden": false, "permalink": "/r/superleague/comments/t7ct2o/saturday_match_thread_round_four/hzhklot/", "subreddit_type": "public", "locked": false, "report_reasons": null, "created": 1646509461.0, "author_flair_text": "Castleford Tigers", "treatment_tags": [], "collapsed": false, "subreddit_name_prefixed": "r/superleague", "controversiality": 0, "depth": 1, "author_flair_background_color": "", "collapsed_because_crowd_control": null, "mod_reports": [], "num_reports": null, "ups": 3}}], "before": null}}, "user_reports": [], "saved": false, "id": "hzhg2hj", "banned_at_utc": null, "mod_reason_title": null, "gilded": 0, "archived": false, "collapsed_reason_code": null, "no_follow": false, "author": "dog_west", "can_mod_post": false, "created_utc": 1646507497.0, "send_replies": true, "parent_id": "t3_t7ct2o", "score": 3, "author_fullname": "t2_cnaq2", "approved_by": null, "mod_note": null, "all_awardings": [], "collapsed": false, "body": "I know it's good for the game etc... for Toulouse to start winning some games, but fuck me I'm relieved haha", "edited": false, "top_awarded_type": null, "author_flair_css_class": "wakefield-trinity-wildcats", "name": "t1_hzhg2hj", "is_submitter": false, "downs": 0, "author_flair_richtext": [{"e": "text", "t": "Wakefield Trinity Wildcats"}], "author_patreon_flair": false, "body_html": "&lt;div class=\"md\"&gt;&lt;p&gt;I know it&amp;#39;s good for the game etc... for Toulouse to start winning some games, but fuck me I&amp;#39;m relieved haha&lt;/p&gt;\n&lt;/div&gt;", "removal_reason": null, "collapsed_reason": null, "distinguished": null, "associated_award": null, "stickied": false, "author_premium": false, "can_gild": false, "gildings": {}, "unrepliable_reason": null, "author_flair_text_color": "dark", "score_hidden": false, "permalink": "/r/superleague/comments/t7ct2o/saturday_match_thread_round_four/hzhg2hj/", "subreddit_type": "public", "locked": false, "report_reasons": null, "created": 1646507497.0, "author_flair_text": "Wakefield Trinity Wildcats", "treatment_tags": [], "link_id": "t3_t7ct2o", "subreddit_name_prefixed": "r/superleague", "controversiality": 0, "depth": 0, "author_flair_background_color": "", "collapsed_because_crowd_control": null, "mod_reports": [], "num_reports": null, "ups": 3}}, {"kind": "t1", "data": {"subreddit_id": "t5_2sjgl", "approved_at_utc": null, "author_is_blocked": false, "comment_type": null, "awarders": [], "mod_reason_by": null, "banned_by": null, "author_flair_type": "richtext", "total_awards_received": 0, "subreddit": "superleague", "author_flair_template_id": "630b4132-7591-11e8-948c-0eac163b86f0", "likes": null, "replies": {"kind": "Listing", "data": {"after": null, "dist": null, "modhash": "", "geo_filter": "", "children": [{"kind": "t1", "data": {"subreddit_id": "t5_2sjgl", "approved_at_utc": null, "author_is_blocked": false, "comment_type": null, "awarders": [], "mod_reason_by": null, "banned_by": null, "author_flair_type": "richtext", "total_awards_received": 0, "subreddit": "superleague", "author_flair_template_id": null, "likes": null, "replies": {"kind": "Listing", "data": {"after": null, "dist": null, "modhash": "", "geo_filter": "", "children": [{"kind": "t1", "data": {"subreddit_id": "t5_2sjgl", "approved_at_utc": null, "author_is_blocked": false, "comment_type": null, "awarders": [], "mod_reason_by": null, "banned_by": null, "author_flair_type": "richtext", "total_awards_received": 0, "subreddit": "superleague", "author_flair_template_id": "630b4132-7591-11e8-948c-0eac163b86f0", "likes": null, "replies": "", "user_reports": [], "saved": false, "id": "hzhf0jw", "banned_at_utc": null, "mod_reason_title": null, "gilded": 0, "archived": false, "collapsed_reason_code": null, "no_follow": true, "author": "galaxy210", "can_mod_post": false, "send_replies": true, "parent_id": "t1_hzhec49", "score": 1, "author_fullname": "t2_9fdg4", "removal_reason": null, "approved_by": null, "mod_note": null, "all_awardings": [], "body": "Sounds like they were a bit indisciplined near the end, not knowing whether a player was going for a DG or making the play", "edited": false, "top_awarded_type": null, "downs": 0, "author_flair_css_class": "salford-city-reds", "name": "t1_hzhf0jw", "is_submitter": false, "collapsed": false, "author_flair_richtext": [{"e": "text", "t": "Salford Red Devils"}], "author_patreon_flair": false, "body_html": "&lt;div class=\"md\"&gt;&lt;p&gt;Sounds like they were a bit indisciplined near the end, not knowing whether a player was going for a DG or making the play&lt;/p&gt;\n&lt;/div&gt;", "gildings": {}, "collapsed_reason": null, "distinguished": null, "associated_award": null, "stickied": false, "author_premium": false, "can_gild": false, "link_id": "t3_t7ct2o", "unrepliable_reason": null, "author_flair_text_color": "dark", "score_hidden": false, "permalink": "/r/superleague/comments/t7ct2o/saturday_match_thread_round_four/hzhf0jw/", "subreddit_type": "public", "locked": false, "report_reasons": null, "created": 1646507040.0, "author_flair_text": "Salford Red Devils", "treatment_tags": [], "created_utc": 1646507040.0, "subreddit_name_prefixed": "r/superleague", "controversiality": 0, "depth": 2, "author_flair_background_color": null, "collapsed_because_crowd_control": null, "mod_reports": [], "num_reports": null, "ups": 1}}], "before": null}}, "user_reports": [], "saved": false, "id": "hzhec49", "banned_at_utc": null, "mod_reason_title": null, "gilded": 0, "archived": false, "collapsed_reason_code": null, "no_follow": true, "author": "Lookdaddyimafarmer", "can_mod_post": false, "created_utc": 1646506744.0, "send_replies": true, "parent_id": "t1_hzhc4ca", "score": 1, "author_fullname": "t2_bw43d", "removal_reason": null, "approved_by": null, "mod_note": null, "all_awardings": [], "body": "Not sure what Gigot was thinking not going for the DG sooner.", "edited": false, "top_awarded_type": null, "author_flair_css_class": "wigan-warriors", "name": "t1_hzhec49", "is_submitter": false, "downs": 0, "author_flair_richtext": [{"e": "text", "t": "Wigan Warriors"}], "author_patreon_flair": false, "body_html": "&lt;div class=\"md\"&gt;&lt;p&gt;Not sure what Gigot was thinking not going for the DG sooner.&lt;/p&gt;\n&lt;/div&gt;", "gildings": {}, "collapsed_reason": null, "distinguished": null, "associated_award": null, "stickied": false, "author_premium": false, "can_gild": false, "link_id": "t3_t7ct2o", "unrepliable_reason": null, "author_flair_text_color": "dark", "score_hidden": false, "permalink": "/r/superleague/comments/t7ct2o/saturday_match_thread_round_four/hzhec49/", "subreddit_type": "public", "locked": false, "report_reasons": null, "created": 1646506744.0, "author_flair_text": "Wigan Warriors", "treatment_tags": [], "collapsed": false, "subreddit_name_prefixed": "r/superleague", "controversiality": 0, "depth": 1, "author_flair_background_color": "", "collapsed_because_crowd_control": null, "mod_reports": [], "num_reports": null, "ups": 1}}], "before": null}}, "user_reports": [], "saved": false, "id": "hzhc4ca", "banned_at_utc": null, "mod_reason_title": null, "gilded": 0, "archived": false, "collapsed_reason_code": null, "no_follow": true, "author": "galaxy210", "can_mod_post": false, "created_utc": 1646505789.0, "send_replies": true, "parent_id": "t3_t7ct2o", "score": 3, "author_fullname": "t2_9fdg4", "approved_by": null, "mod_note": null, "all_awardings": [], "collapsed": false, "body": "Ah man, gutted for Tolouse here. Why they didn't take the DG earlier when they had the chances", "edited": false, "top_awarded_type": null, "author_flair_css_class": "salford-city-reds", "name": "t1_hzhc4ca", "is_submitter": false, "downs": 0, "author_flair_richtext": [{"e": "text", "t": "Salford Red Devils"}], "author_patreon_flair": false, "body_html": "&lt;div class=\"md\"&gt;&lt;p&gt;Ah man, gutted for Tolouse here. Why they didn&amp;#39;t take the DG earlier when they had the chances&lt;/p&gt;\n&lt;/div&gt;", "removal_reason": null, "collapsed_reason": null, "distinguished": null, "associated_award": null, "stickied": false, "author_premium": false, "can_gild": false, "gildings": {}, "unrepliable_reason": null, "author_flair_text_color": "dark", "score_hidden": false, "permalink": "/r/superleague/comments/t7ct2o/saturday_match_thread_round_four/hzhc4ca/", "subreddit_type": "public", "locked": false, "report_reasons": null, "created": 1646505789.0, "author_flair_text": "Salford Red Devils", "treatment_tags": [], "link_id": "t3_t7ct2o", "subreddit_name_prefixed": "r/superleague", "controversiality": 0, "depth": 0, "author_flair_background_color": null, "collapsed_because_crowd_control": null, "mod_reports": [], "num_reports": null, "ups": 3}}, {"kind": "t1", "data": {"subreddit_id": "t5_2sjgl", "approved_at_utc": null, "author_is_blocked": false, "comment_type": null, "awarders": [], "mod_reason_by": null, "banned_by": null, "author_flair_type": "richtext", "total_awards_received": 0, "subreddit": "superleague", "author_flair_template_id": "5a64ea88-7591-11e8-aadb-0e6a5a2ce690", "likes": null, "replies": "", "user_reports": [], "saved": false, "id": "hzhbrb1", "banned_at_utc": null, "mod_reason_title": null, "gilded": 0, "archived": false, "collapsed_reason_code": null, "no_follow": true, "author": "toddstar", "can_mod_post": false, "created_utc": 1646505635.0, "send_replies": true, "parent_id": "t3_t7ct2o", "score": 1, "author_fullname": "t2_2mbgoxfw", "approved_by": null, "mod_note": null, "all_awardings": [], "collapsed": false, "body": "Wigan to steal the win in this set", "edited": false, "top_awarded_type": null, "author_flair_css_class": "leeds-rhinos-rect", "name": "t1_hzhbrb1", "is_submitter": false, "downs": 0, "author_flair_richtext": [{"e": "text", "t": "Leeds Rhinos"}], "author_patreon_flair": false, "body_html": "&lt;div class=\"md\"&gt;&lt;p&gt;Wigan to steal the win in this set&lt;/p&gt;\n&lt;/div&gt;", "removal_reason": null, "collapsed_reason": null, "distinguished": null, "associated_award": null, "stickied": false, "author_premium": true, "can_gild": false, "gildings": {}, "unrepliable_reason": null, "author_flair_text_color": "dark", "score_hidden": false, "permalink": "/r/superleague/comments/t7ct2o/saturday_match_thread_round_four/hzhbrb1/", "subreddit_type": "public", "locked": false, "report_reasons": null, "created": 1646505635.0, "author_flair_text": "Leeds Rhinos", "treatment_tags": [], "link_id": "t3_t7ct2o", "subreddit_name_prefixed": "r/superleague", "controversiality": 0, "depth": 0, "author_flair_background_color": null, "collapsed_because_crowd_control": null, "mod_reports": [], "num_reports": null, "ups": 1}}, {"kind": "t1", "data": {"subreddit_id": "t5_2sjgl", "approved_at_utc": null, "author_is_blocked": false, "comment_type": null, "awarders": [], "mod_reason_by": null, "banned_by": null, "author_flair_type": "richtext", "total_awards_received": 0, "subreddit": "superleague", "author_flair_template_id": "980ea270-7591-11e8-ade5-0e47aad96570", "likes": null, "replies": {"kind": "Listing", "data": {"after": null, "dist": null, "modhash": "", "geo_filter": "", "children": [{"kind": "t1", "data": {"subreddit_id": "t5_2sjgl", "approved_at_utc": null, "author_is_blocked": false, "comment_type": null, "awarders": [], "mod_reason_by": null, "banned_by": null, "author_flair_type": "richtext", "total_awards_received": 0, "subreddit": "superleague", "author_flair_template_id": "5a64ea88-7591-11e8-aadb-0e6a5a2ce690", "likes": null, "replies": "", "user_reports": [], "saved": false, "id": "hzhbco4", "banned_at_utc": null, "mod_reason_title": null, "gilded": 0, "archived": false, "collapsed_reason_code": null, "no_follow": true, "author": "toddstar", "can_mod_post": false, "created_utc": 1646505463.0, "send_replies": true, "parent_id": "t1_hzhazgn", "score": 1, "author_fullname": "t2_2mbgoxfw", "removal_reason": null, "approved_by": null, "mod_note": null, "all_awardings": [], "body": "Given they've already drops 2 over I'd take the commentators comments with pinch of salt", "edited": false, "top_awarded_type": null, "author_flair_css_class": "leeds-rhinos-rect", "name": "t1_hzhbco4", "is_submitter": false, "downs": 0, "author_flair_richtext": [{"e": "text", "t": "Leeds Rhinos"}], "author_patreon_flair": false, "body_html": "&lt;div class=\"md\"&gt;&lt;p&gt;Given they&amp;#39;ve already drops 2 over I&amp;#39;d take the commentators comments with pinch of salt&lt;/p&gt;\n&lt;/div&gt;", "gildings": {}, "collapsed_reason": null, "distinguished": null, "associated_award": null, "stickied": false, "author_premium": true, "can_gild": false, "link_id": "t3_t7ct2o", "unrepliable_reason": null, "author_flair_text_color": "dark", "score_hidden": false, "permalink": "/r/superleague/comments/t7ct2o/saturday_match_thread_round_four/hzhbco4/", "subreddit_type": "public", "locked": false, "report_reasons": null, "created": 1646505463.0, "author_flair_text": "Leeds Rhinos", "treatment_tags": [], "collapsed": false, "subreddit_name_prefixed": "r/superleague", "controversiality": 0, "depth": 1, "author_flair_background_color": null, "collapsed_because_crowd_control": null, "mod_reports": [], "num_reports": null, "ups": 1}}, {"kind": "t1", "data": {"subreddit_id": "t5_2sjgl", "approved_at_utc": null, "author_is_blocked": false, "comment_type": null, "awarders": [], "mod_reason_by": null, "banned_by": null, "author_flair_type": "richtext", "total_awards_received": 0, "subreddit": "superleague", "author_flair_template_id": "630b4132-7591-11e8-948c-0eac163b86f0", "likes": null, "replies": "", "user_reports": [], "saved": false, "id": "hzhb7fn", "banned_at_utc": null, "mod_reason_title": null, "gilded": 0, "archived": false, "collapsed_reason_code": null, "no_follow": true, "author": "galaxy210", "can_mod_post": false, "created_utc": 1646505399.0, "send_replies": true, "parent_id": "t1_hzhazgn", "score": 1, "author_fullname": "t2_9fdg4", "removal_reason": null, "approved_by": null, "mod_note": null, "all_awardings": [], "body": "Agree, I'd love Tolouse to get that first win earlier, and start building confidence for a proper competition like with London. Would make for a generally better season", "edited": false, "top_awarded_type": null, "author_flair_css_class": "salford-city-reds", "name": "t1_hzhb7fn", "is_submitter": false, "downs": 0, "author_flair_richtext": [{"e": "text", "t": "Salford Red Devils"}], "author_patreon_flair": false, "body_html": "&lt;div class=\"md\"&gt;&lt;p&gt;Agree, I&amp;#39;d love Tolouse to get that first win earlier, and start building confidence for a proper competition like with London. Would make for a generally better season&lt;/p&gt;\n&lt;/div&gt;", "gildings": {}, "collapsed_reason": null, "distinguished": null, "associated_award": null, "stickied": false, "author_premium": false, "can_gild": false, "link_id": "t3_t7ct2o", "unrepliable_reason": null, "author_flair_text_color": "dark", "score_hidden": false, "permalink": "/r/superleague/comments/t7ct2o/saturday_match_thread_round_four/hzhb7fn/", "subreddit_type": "public", "locked": false, "report_reasons": null, "created": 1646505399.0, "author_flair_text": "Salford Red Devils", "treatment_tags": [], "collapsed": false, "subreddit_name_prefixed": "r/superleague", "controversiality": 0, "depth": 1, "author_flair_background_color": null, "collapsed_because_crowd_control": null, "mod_reports": [], "num_reports": null, "ups": 1}}], "before": null}}, "user_reports": [], "saved": false, "id": "hzhazgn", "banned_at_utc": null, "mod_reason_title": null, "gilded": 0, "archived": false, "collapsed_reason_code": null, "no_follow": true, "author": "TexturePackReview", "can_mod_post": false, "created_utc": 1646505304.0, "send_replies": true, "parent_id": "t3_t7ct2o", "score": 1, "author_fullname": "t2_64usn", "approved_by": null, "mod_note": null, "all_awardings": [], "collapsed": false, "body": "When did Hardaker learn how to kick? Be gutted if Toulouse end up losing, sounds like they had plenty of chances for a drop goal", "edited": false, "top_awarded_type": null, "author_flair_css_class": "wigan-warriors", "name": "t1_hzhazgn", "is_submitter": false, "downs": 0, "author_flair_richtext": [{"e": "text", "t": "Actually a Leeds fan"}], "author_patreon_flair": false, "body_html": "&lt;div class=\"md\"&gt;&lt;p&gt;When did Hardaker learn how to kick? Be gutted if Toulouse end up losing, sounds like they had plenty of chances for a drop goal&lt;/p&gt;\n&lt;/div&gt;", "removal_reason": null, "collapsed_reason": null, "distinguished": null, "associated_award": null, "stickied": false, "author_premium": false, "can_gild": false, "gildings": {}, "unrepliable_reason": null, "author_flair_text_color": "dark", "score_hidden": false, "permalink": "/r/superleague/comments/t7ct2o/saturday_match_thread_round_four/hzhazgn/", "subreddit_type": "public", "locked": false, "report_reasons": null, "created": 1646505304.0, "author_flair_text": "Actually a Leeds fan", "treatment_tags": [], "link_id": "t3_t7ct2o", "subreddit_name_prefixed": "r/superleague", "controversiality": 0, "depth": 0, "author_flair_background_color": null, "collapsed_because_crowd_control": null, "mod_reports": [], "num_reports": null, "ups": 1}}, {"kind": "t1", "data": {"subreddit_id": "t5_2sjgl", "approved_at_utc": null, "author_is_blocked": false, "comment_type": null, "awarders": [], "mod_reason_by": null, "banned_by": null, "author_flair_type": "richtext", "total_awards_received": 0, "subreddit": "superleague", "author_flair_template_id": "6fa1e842-7591-11e8-a82b-0e9264a107b8", "likes": null, "replies": "", "user_reports": [], "saved": false, "id": "hzh9rms", "banned_at_utc": null, "mod_reason_title": null, "gilded": 0, "archived": false, "collapsed_reason_code": null, "no_follow": true, "author": "RubberTowelThud", "can_mod_post": false, "created_utc": 1646504787.0, "send_replies": true, "parent_id": "t3_t7ct2o", "score": 1, "author_fullname": "t2_8ge209xb", "approved_by": null, "mod_note": null, "all_awardings": [], "collapsed": false, "body": "Wasn't expecting wigan to be regretting the missed kicked at 10-0 after 9 minutes but here we are", "edited": false, "top_awarded_type": null, "author_flair_css_class": "st-helens", "name": "t1_hzh9rms", "is_submitter": false, "downs": 0, "author_flair_richtext": [{"e": "text", "t": "St Helens"}], "author_patreon_flair": false, "body_html": "&lt;div class=\"md\"&gt;&lt;p&gt;Wasn&amp;#39;t expecting wigan to be regretting the missed kicked at 10-0 after 9 minutes but here we are&lt;/p&gt;\n&lt;/div&gt;", "removal_reason": null, "collapsed_reason": null, "distinguished": null, "associated_award": null, "stickied": false, "author_premium": false, "can_gild": false, "gildings": {}, "unrepliable_reason": null, "author_flair_text_color": "dark", "score_hidden": false, "permalink": "/r/superleague/comments/t7ct2o/saturday_match_thread_round_four/hzh9rms/", "subreddit_type": "public", "locked": false, "report_reasons": null, "created": 1646504787.0, "author_flair_text": "St Helens", "treatment_tags": [], "link_id": "t3_t7ct2o", "subreddit_name_prefixed": "r/superleague", "controversiality": 0, "depth": 0, "author_flair_background_color": null, "collapsed_because_crowd_control": null, "mod_reports": [], "num_reports": null, "ups": 1}}, {"kind": "t1", "data": {"subreddit_id": "t5_2sjgl", "approved_at_utc": null, "author_is_blocked": false, "comment_type": null, "awarders": [], "mod_reason_by": null, "banned_by": null, "author_flair_type": "richtext", "total_awards_received": 0, "subreddit": "superleague", "author_flair_template_id": "980ea270-7591-11e8-ade5-0e47aad96570", "likes": null, "replies": {"kind": "Listing", "data": {"after": null, "dist": null, "modhash": "", "geo_filter": "", "children": [{"kind": "t1", "data": {"subreddit_id": "t5_2sjgl", "approved_at_utc": null, "author_is_blocked": false, "comment_type": null, "awarders": [], "mod_reason_by": null, "banned_by": null, "author_flair_type": "richtext", "total_awards_received": 0, "subreddit": "superleague", "author_flair_template_id": "630b4132-7591-11e8-948c-0eac163b86f0", "likes": null, "replies": {"kind": "Listing", "data": {"after": null, "dist": null, "modhash": "", "geo_filter": "", "children": [{"kind": "t1", "data": {"subreddit_id": "t5_2sjgl", "approved_at_utc": null, "author_is_blocked": false, "comment_type": null, "awarders": [], "mod_reason_by": null, "banned_by": null, "author_flair_type": "richtext", "total_awards_received": 0, "subreddit": "superleague", "author_flair_template_id": "980ea270-7591-11e8-ade5-0e47aad96570", "likes": null, "replies": {"kind": "Listing", "data": {"after": null, "dist": null, "modhash": "", "geo_filter": "", "children": [{"kind": "t1", "data": {"subreddit_id": "t5_2sjgl", "approved_at_utc": null, "author_is_blocked": false, "comment_type": null, "awarders": [], "mod_reason_by": null, "banned_by": null, "author_flair_type": "richtext", "total_awards_received": 0, "subreddit": "superleague", "author_flair_template_id": "630b4132-7591-11e8-948c-0eac163b86f0", "likes": null, "replies": "", "user_reports": [], "saved": false, "id": "hzha5ni", "banned_at_utc": null, "mod_reason_title": null, "gilded": 0, "archived": false, "collapsed_reason_code": null, "no_follow": true, "author": "galaxy210", "can_mod_post": false, "send_replies": true, "parent_id": "t1_hzh9ozb", "score": 1, "author_fullname": "t2_9fdg4", "removal_reason": null, "approved_by": null, "mod_note": null, "all_awardings": [], "collapsed": false, "body": "One more try I reckon to lock this up, but a DG will be good reassurance", "edited": false, "top_awarded_type": null, "author_flair_css_class": "salford-city-reds", "name": "t1_hzha5ni", "is_submitter": false, "downs": 0, "author_flair_richtext": [{"e": "text", "t": "Salford Red Devils"}], "author_patreon_flair": false, "body_html": "&lt;div class=\"md\"&gt;&lt;p&gt;One more try I reckon to lock this up, but a DG will be good reassurance&lt;/p&gt;\n&lt;/div&gt;", "gildings": {}, "collapsed_reason": null, "distinguished": null, "associated_award": null, "stickied": false, "author_premium": false, "can_gild": false, "link_id": "t3_t7ct2o", "unrepliable_reason": null, "author_flair_text_color": "dark", "score_hidden": false, "permalink": "/r/superleague/comments/t7ct2o/saturday_match_thread_round_four/hzha5ni/", "subreddit_type": "public", "locked": false, "report_reasons": null, "created": 1646504955.0, "author_flair_text": "Salford Red Devils", "treatment_tags": [], "created_utc": 1646504955.0, "subreddit_name_prefixed": "r/superleague", "controversiality": 0, "depth": 3, "author_flair_background_color": null, "collapsed_because_crowd_control": null, "mod_reports": [], "num_reports": null, "ups": 1}}], "before": null}}, "user_reports": [], "saved": false, "id": "hzh9ozb", "banned_at_utc": null, "mod_reason_title": null, "gilded": 0, "archived": false, "collapsed_reason_code": null, "no_follow": true, "author": "TexturePackReview", "can_mod_post": false, "send_replies": true, "parent_id": "t1_hzh8vum", "score": 1, "author_fullname": "t2_64usn", "removal_reason": null, "approved_by": null, "mod_note": null, "all_awardings": [], "body": "Think they need one more, or a DG/FG", "edited": false, "top_awarded_type": null, "downs": 0, "author_flair_css_class": "wigan-warriors", "name": "t1_hzh9ozb", "is_submitter": false, "collapsed": false, "author_flair_richtext": [{"e": "text", "t": "Actually a Leeds fan"}], "author_patreon_flair": false, "body_html": "&lt;div class=\"md\"&gt;&lt;p&gt;Think they need one more, or a DG/FG&lt;/p&gt;\n&lt;/div&gt;", "gildings": {}, "collapsed_reason": null, "distinguished": null, "associated_award": null, "stickied": false, "author_premium": false, "can_gild": false, "link_id": "t3_t7ct2o", "unrepliable_reason": null, "author_flair_text_color": "dark", "score_hidden": false, "permalink": "/r/superleague/comments/t7ct2o/saturday_match_thread_round_four/hzh9ozb/", "subreddit_type": "public", "locked": false, "report_reasons": null, "created": 1646504755.0, "author_flair_text": "Actually a Leeds fan", "treatment_tags": [], "created_utc": 1646504755.0, "subreddit_name_prefixed": "r/superleague", "controversiality": 0, "depth": 2, "author_flair_background_color": null, "collapsed_because_crowd_control": null, "mod_reports": [], "num_reports": null, "ups": 1}}], "before": null}}, "user_reports": [], "saved": false, "id": "hzh8vum", "banned_at_utc": null, "mod_reason_title": null, "gilded": 0, "archived": false, "collapsed_reason_code": null, "no_follow": true, "author": "galaxy210", "can_mod_post": false, "created_utc": 1646504411.0, "send_replies": true, "parent_id": "t1_hzh7abv", "score": 1, "author_fullname": "t2_9fdg4", "removal_reason": null, "approved_by": null, "mod_note": null, "all_awardings": [], "body": "Surely not.", "edited": false, "top_awarded_type": null, "author_flair_css_class": "salford-city-reds", "name": "t1_hzh8vum", "is_submitter": false, "downs": 0, "author_flair_richtext": [{"e": "text", "t": "Salford Red Devils"}], "author_patreon_flair": false, "body_html": "&lt;div class=\"md\"&gt;&lt;p&gt;Surely not.&lt;/p&gt;\n&lt;/div&gt;", "gildings": {}, "collapsed_reason": null, "distinguished": null, "associated_award": null, "stickied": false, "author_premium": false, "can_gild": false, "link_id": "t3_t7ct2o", "unrepliable_reason": null, "author_flair_text_color": "dark", "score_hidden": false, "permalink": "/r/superleague/comments/t7ct2o/saturday_match_thread_round_four/hzh8vum/", "subreddit_type": "public", "locked": false, "report_reasons": null, "created": 1646504411.0, "author_flair_text": "Salford Red Devils", "treatment_tags": [], "collapsed": false, "subreddit_name_prefixed": "r/superleague", "controversiality": 0, "depth": 1, "author_flair_background_color": null, "collapsed_because_crowd_control": null, "mod_reports": [], "num_reports": null, "ups": 1}}], "before": null}}, "user_reports": [], "saved": false, "id": "hzh7abv", "banned_at_utc": null, "mod_reason_title": null, "gilded": 0, "archived": false, "collapsed_reason_code": null, "no_follow": true, "author": "TexturePackReview", "can_mod_post": false, "created_utc": 1646503727.0, "send_replies": true, "parent_id": "t3_t7ct2o", "score": 1, "author_fullname": "t2_64usn", "approved_by": null, "mod_note": null, "all_awardings": [], "collapsed": false, "body": "They couldn't could they...", "edited": false, "top_awarded_type": null, "author_flair_css_class": "wigan-warriors", "name": "t1_hzh7abv", "is_submitter": false, "downs": 0, "author_flair_richtext": [{"e": "text", "t": "Actually a Leeds fan"}], "author_patreon_flair": false, "body_html": "&lt;div class=\"md\"&gt;&lt;p&gt;They couldn&amp;#39;t could they...&lt;/p&gt;\n&lt;/div&gt;", "removal_reason": null, "collapsed_reason": null, "distinguished": null, "associated_award": null, "stickied": false, "author_premium": false, "can_gild": false, "gildings": {}, "unrepliable_reason": null, "author_flair_text_color": "dark", "score_hidden": false, "permalink": "/r/superleague/comments/t7ct2o/saturday_match_thread_round_four/hzh7abv/", "subreddit_type": "public", "locked": false, "report_reasons": null, "created": 1646503727.0, "author_flair_text": "Actually a Leeds fan", "treatment_tags": [], "link_id": "t3_t7ct2o", "subreddit_name_prefixed": "r/superleague", "controversiality": 0, "depth": 0, "author_flair_background_color": null, "collapsed_because_crowd_control": null, "mod_reports": [], "num_reports": null, "ups": 1}}, {"kind": "t1", "data": {"subreddit_id": "t5_2sjgl", "approved_at_utc": null, "author_is_blocked": false, "comment_type": null, "awarders": [], "mod_reason_by": null, "banned_by": null, "author_flair_type": "richtext", "total_awards_received": 0, "subreddit": "superleague", "author_flair_template_id": "630b4132-7591-11e8-948c-0eac163b86f0", "likes": null, "replies": "", "user_reports": [], "saved": false, "id": "hzh6ws0", "banned_at_utc": null, "mod_reason_title": null, "gilded": 0, "archived": false, "collapsed_reason_code": null, "no_follow": true, "author": "galaxy210", "can_mod_post": false, "created_utc": 1646503564.0, "send_replies": true, "parent_id": "t3_t7ct2o", "score": 1, "author_fullname": "t2_9fdg4", "approved_by": null, "mod_note": null, "all_awardings": [], "collapsed": false, "body": "Don't think we'll be seeing Harry Smith again for a few games", "edited": false, "top_awarded_type": null, "author_flair_css_class": "salford-city-reds", "name": "t1_hzh6ws0", "is_submitter": false, "downs": 0, "author_flair_richtext": [{"e": "text", "t": "Salford Red Devils"}], "author_patreon_flair": false, "body_html": "&lt;div class=\"md\"&gt;&lt;p&gt;Don&amp;#39;t think we&amp;#39;ll be seeing Harry Smith again for a few games&lt;/p&gt;\n&lt;/div&gt;", "removal_reason": null, "collapsed_reason": null, "distinguished": null, "associated_award": null, "stickied": false, "author_premium": false, "can_gild": false, "gildings": {}, "unrepliable_reason": null, "author_flair_text_color": "dark", "score_hidden": false, "permalink": "/r/superleague/comments/t7ct2o/saturday_match_thread_round_four/hzh6ws0/", "subreddit_type": "public", "locked": false, "report_reasons": null, "created": 1646503564.0, "author_flair_text": "Salford Red Devils", "treatment_tags": [], "link_id": "t3_t7ct2o", "subreddit_name_prefixed": "r/superleague", "controversiality": 0, "depth": 0, "author_flair_background_color": null, "collapsed_because_crowd_control": null, "mod_reports": [], "num_reports": null, "ups": 1}}, {"kind": "t1", "data": {"subreddit_id": "t5_2sjgl", "approved_at_utc": null, "author_is_blocked": false, "comment_type": null, "awarders": [], "mod_reason_by": null, "banned_by": null, "author_flair_type": "richtext", "total_awards_received": 0, "subreddit": "superleague", "author_flair_template_id": "5a64ea88-7591-11e8-aadb-0e6a5a2ce690", "likes": null, "replies": "", "user_reports": [], "saved": false, "id": "hzh4bc7", "banned_at_utc": null, "mod_reason_title": null, "gilded": 0, "archived": false, "collapsed_reason_code": null, "no_follow": true, "author": "toddstar", "can_mod_post": false, "created_utc": 1646502480.0, "send_replies": true, "parent_id": "t3_t7ct2o", "score": 1, "author_fullname": "t2_2mbgoxfw", "approved_by": null, "mod_note": null, "all_awardings": [], "collapsed": false, "body": "Miski sounds like he's having a shocker for wigan", "edited": false, "top_awarded_type": null, "author_flair_css_class": "leeds-rhinos-rect", "name": "t1_hzh4bc7", "is_submitter": false, "downs": 0, "author_flair_richtext": [{"e": "text", "t": "Leeds Rhinos"}], "author_patreon_flair": false, "body_html": "&lt;div class=\"md\"&gt;&lt;p&gt;Miski sounds like he&amp;#39;s having a shocker for wigan&lt;/p&gt;\n&lt;/div&gt;", "removal_reason": null, "collapsed_reason": null, "distinguished": null, "associated_award": null, "stickied": false, "author_premium": true, "can_gild": false, "gildings": {}, "unrepliable_reason": null, "author_flair_text_color": "dark", "score_hidden": false, "permalink": "/r/superleague/comments/t7ct2o/saturday_match_thread_round_four/hzh4bc7/", "subreddit_type": "public", "locked": false, "report_reasons": null, "created": 1646502480.0, "author_flair_text": "Leeds Rhinos", "treatment_tags": [], "link_id": "t3_t7ct2o", "subreddit_name_prefixed": "r/superleague", "controversiality": 0, "depth": 0, "author_flair_background_color": null, "collapsed_because_crowd_control": null, "mod_reports": [], "num_reports": null, "ups": 1}}, {"kind": "t1", "data": {"subreddit_id": "t5_2sjgl", "approved_at_utc": null, "author_is_blocked": false, "comment_type": null, "awarders": [], "mod_reason_by": null, "banned_by": null, "author_flair_type": "richtext", "total_awards_received": 0, "subreddit": "superleague", "author_flair_template_id": "630b4132-7591-11e8-948c-0eac163b86f0", "likes": null, "replies": "", "user_reports": [], "saved": false, "id": "hzh3g2t", "banned_at_utc": null, "mod_reason_title": null, "gilded": 0, "archived": false, "collapsed_reason_code": null, "no_follow": true, "author": "galaxy210", "can_mod_post": false, "created_utc": 1646502116.0, "send_replies": true, "parent_id": "t3_t7ct2o", "score": 1, "author_fullname": "t2_9fdg4", "approved_by": null, "mod_note": null, "all_awardings": [], "collapsed": false, "body": "well here's a turn up, Wigan now behind", "edited": false, "top_awarded_type": null, "author_flair_css_class": "salford-city-reds", "name": "t1_hzh3g2t", "is_submitter": false, "downs": 0, "author_flair_richtext": [{"e": "text", "t": "Salford Red Devils"}], "author_patreon_flair": false, "body_html": "&lt;div class=\"md\"&gt;&lt;p&gt;well here&amp;#39;s a turn up, Wigan now behind&lt;/p&gt;\n&lt;/div&gt;", "removal_reason": null, "collapsed_reason": null, "distinguished": null, "associated_award": null, "stickied": false, "author_premium": false, "can_gild": false, "gildings": {}, "unrepliable_reason": null, "author_flair_text_color": "dark", "score_hidden": false, "permalink": "/r/superleague/comments/t7ct2o/saturday_match_thread_round_four/hzh3g2t/", "subreddit_type": "public", "locked": false, "report_reasons": null, "created": 1646502116.0, "author_flair_text": "Salford Red Devils", "treatment_tags": [], "link_id": "t3_t7ct2o", "subreddit_name_prefixed": "r/superleague", "controversiality": 0, "depth": 0, "author_flair_background_color": null, "collapsed_because_crowd_control": null, "mod_reports": [], "num_reports": null, "ups": 1}}, {"kind": "t1", "data": {"subreddit_id": "t5_2sjgl", "approved_at_utc": null, "author_is_blocked": false, "comment_type": null, "awarders": [], "mod_reason_by": null, "banned_by": null, "author_flair_type": "richtext", "total_awards_received": 0, "subreddit": "superleague", "author_flair_template_id": "6fa1e842-7591-11e8-a82b-0e9264a107b8", "likes": null, "replies": "", "user_reports": [], "saved": false, "id": "hzh3esc", "banned_at_utc": null, "mod_reason_title": null, "gilded": 0, "archived": false, "collapsed_reason_code": null, "no_follow": true, "author": "RubberTowelThud", "can_mod_post": false, "created_utc": 1646502101.0, "send_replies": true, "parent_id": "t3_t7ct2o", "score": 1, "author_fullname": "t2_8ge209xb", "approved_by": null, "mod_note": null, "all_awardings": [], "collapsed": false, "body": "Allez", "edited": false, "top_awarded_type": null, "author_flair_css_class": "st-helens", "name": "t1_hzh3esc", "is_submitter": false, "downs": 0, "author_flair_richtext": [{"e": "text", "t": "St Helens"}], "author_patreon_flair": false, "body_html": "&lt;div class=\"md\"&gt;&lt;p&gt;Allez&lt;/p&gt;\n&lt;/div&gt;", "removal_reason": null, "collapsed_reason": null, "distinguished": null, "associated_award": null, "stickied": false, "author_premium": false, "can_gild": false, "gildings": {}, "unrepliable_reason": null, "author_flair_text_color": "dark", "score_hidden": false, "permalink": "/r/superleague/comments/t7ct2o/saturday_match_thread_round_four/hzh3esc/", "subreddit_type": "public", "locked": false, "report_reasons": null, "created": 1646502101.0, "author_flair_text": "St Helens", "treatment_tags": [], "link_id": "t3_t7ct2o", "subreddit_name_prefixed": "r/superleague", "controversiality": 0, "depth": 0, "author_flair_background_color": null, "collapsed_because_crowd_control": null, "mod_reports": [], "num_reports": null, "ups": 1}}, {"kind": "t1", "data": {"subreddit_id": "t5_2sjgl", "approved_at_utc": null, "author_is_blocked": false, "comment_type": null, "awarders": [], "mod_reason_by": null, "banned_by": null, "author_flair_type": "richtext", "total_awards_received": 0, "subreddit": "superleague", "author_flair_template_id": "b4fab09e-1260-11ec-b554-264260723aef", "likes": null, "replies": "", "user_reports": [], "saved": false, "id": "hzgylvd", "banned_at_utc": null, "mod_reason_title": null, "gilded": 0, "archived": false, "collapsed_reason_code": null, "no_follow": true, "author": "GingertronMk1", "can_mod_post": false, "created_utc": 1646500062.0, "send_replies": true, "parent_id": "t3_t7ct2o", "score": 1, "author_fullname": "t2_djqgy", "approved_by": null, "mod_note": null, "all_awardings": [], "collapsed": false, "body": "Oh hey Toulouse is already losing", "edited": false, "top_awarded_type": null, "author_flair_css_class": "hkrnewsq", "name": "t1_hzgylvd", "is_submitter": false, "downs": 0, "author_flair_richtext": [{"e": "text", "t": "Hull KR"}], "author_patreon_flair": false, "body_html": "&lt;div class=\"md\"&gt;&lt;p&gt;Oh hey Toulouse is already losing&lt;/p&gt;\n&lt;/div&gt;", "removal_reason": null, "collapsed_reason": null, "distinguished": null, "associated_award": null, "stickied": false, "author_premium": false, "can_gild": false, "gildings": {}, "unrepliable_reason": null, "author_flair_text_color": "dark", "score_hidden": false, "permalink": "/r/superleague/comments/t7ct2o/saturday_match_thread_round_four/hzgylvd/", "subreddit_type": "public", "locked": false, "report_reasons": null, "created": 1646500062.0, "author_flair_text": "Hull KR", "treatment_tags": [], "link_id": "t3_t7ct2o", "subreddit_name_prefixed": "r/superleague", "controversiality": 0, "depth": 0, "author_flair_background_color": null, "collapsed_because_crowd_control": null, "mod_reports": [], "num_reports": null, "ups": 1}}, {"kind": "t1", "data": {"subreddit_id": "t5_2sjgl", "approved_at_utc": null, "author_is_blocked": false, "comment_type": null, "awarders": [], "mod_reason_by": null, "banned_by": null, "author_flair_type": "richtext", "total_awards_received": 0, "subreddit": "superleague", "author_flair_template_id": "5a64ea88-7591-11e8-aadb-0e6a5a2ce690", "likes": null, "replies": "", "user_reports": [], "saved": false, "id": "hzgxkkp", "banned_at_utc": null, "mod_reason_title": null, "gilded": 0, "archived": false, "collapsed_reason_code": null, "no_follow": true, "author": "toddstar", "can_mod_post": false, "created_utc": 1646499630.0, "send_replies": true, "parent_id": "t3_t7ct2o", "score": 1, "author_fullname": "t2_2mbgoxfw", "approved_by": null, "mod_note": null, "all_awardings": [], "collapsed": false, "body": "https://mixlr.com/wigantv if anyone wants to listen to the game", "edited": false, "top_awarded_type": null, "author_flair_css_class": "leeds-rhinos-rect", "name": "t1_hzgxkkp", "is_submitter": false, "downs": 0, "author_flair_richtext": [{"e": "text", "t": "Leeds Rhinos"}], "author_patreon_flair": false, "body_html": "&lt;div class=\"md\"&gt;&lt;p&gt;&lt;a href=\"https://mixlr.com/wigantv\"&gt;https://mixlr.com/wigantv&lt;/a&gt; if anyone wants to listen to the game&lt;/p&gt;\n&lt;/div&gt;", "removal_reason": null, "collapsed_reason": null, "distinguished": null, "associated_award": null, "stickied": false, "author_premium": true, "can_gild": false, "gildings": {}, "unrepliable_reason": null, "author_flair_text_color": "dark", "score_hidden": false, "permalink": "/r/superleague/comments/t7ct2o/saturday_match_thread_round_four/hzgxkkp/", "subreddit_type": "public", "locked": false, "report_reasons": null, "created": 1646499630.0, "author_flair_text": "Leeds Rhinos", "treatment_tags": [], "link_id": "t3_t7ct2o", "subreddit_name_prefixed": "r/superleague", "controversiality": 0, "depth": 0, "author_flair_background_color": null, "collapsed_because_crowd_control": null, "mod_reports": [], "num_reports": null, "ups": 1}}], "before": null}}]